desc_bpz/MLab_coe_py3.py
desc_bpz/__init__.py
desc_bpz/_version.py
desc_bpz/bpz_tools_py3.py
desc_bpz/coeio_py3.py
desc_bpz/coetools_py3.py
desc_bpz/compress2_py3.py
desc_bpz/func_py3.py
desc_bpz/paths.py
desc_bpz/prior_from_dict.py
desc_bpz/prior_hdfn_gen.py
desc_bpz/spline_py3.py
desc_bpz/useful_py3.py
desc_bpz/version.py
desc_bpz/will_tools_py3.py
desc_bpz/data_files/AB/El_B2004a.DC2LSST_g.AB
desc_bpz/data_files/FILTER/DC2LSST_g.res
desc_bpz/data_files/FILTER/DC2LSST_i.res
desc_bpz/data_files/FILTER/DC2LSST_r.res
desc_bpz/data_files/FILTER/DC2LSST_u.res
desc_bpz/data_files/FILTER/DC2LSST_y.res
desc_bpz/data_files/FILTER/DC2LSST_z.res
desc_bpz/data_files/SED/CWWSB4.list
desc_bpz/data_files/SED/El_B2004a.sed
desc_bpz/data_files/SED/Im_B2004a.sed
desc_bpz/data_files/SED/SB2_B2004a.sed
desc_bpz/data_files/SED/SB3_B2004a.sed
desc_bpz/data_files/SED/Sbc_B2004a.sed
desc_bpz/data_files/SED/Scd_B2004a.sed
desc_bpz/data_files/SED/ssp_25Myr_z008.sed
desc_bpz/data_files/SED/ssp_5Myr_z008.sed
desc_bpz/scripts/CSDC2114_test.columns
desc_bpz/scripts/bpz.py
desc_bpz-0.3.2.dist-info/LICENSE
desc_bpz-0.3.2.dist-info/METADATA
desc_bpz-0.3.2.dist-info/WHEEL
desc_bpz-0.3.2.dist-info/top_level.txt
desc_bpz-0.3.2.dist-info/RECORD
