Metadata-Version: 2.2
Name: desc-bpz
Version: 0.3.2
Summary: Python3 version of BPZ used in DESC
Author-email: "Noel Benitez, Dan Coe, Will Hartley, Sam Schmidt, Joe Zuntz, LSST DESC PZWG" <samuel.j.schmidt@gmail.com>
License: MIT License
Project-URL: Source Code, https://github.com/LSSTDESC/DESC_BPZ
Classifier: Development Status :: 4 - Beta
Classifier: License :: OSI Approved :: MIT License
Classifier: Intended Audience :: Developers
Classifier: Intended Audience :: Science/Research
Classifier: Operating System :: OS Independent
Classifier: Programming Language :: Python
Requires-Python: >=3.10
License-File: LICENSE
Requires-Dist: numpy
Requires-Dist: scipy
Requires-Dist: pandas>=1.1
Requires-Dist: h5py
Provides-Extra: dev
Requires-Dist: pre-commit; extra == "dev"
Requires-Dist: pytest; extra == "dev"
Requires-Dist: pytest-cov; extra == "dev"
